monsterlib/__init__.py
monsterlib/cli.py
monsterlib/core.py
monsterlib/version.py
monstrelib-0.5.0.dist-info/METADATA
monstrelib-0.5.0.dist-info/WHEEL
monstrelib-0.5.0.dist-info/entry_points.txt
monstrelib-0.5.0.dist-info/top_level.txt
monstrelib-0.5.0.dist-info/RECORD
