Metadata-Version: 2.4
Name: monstrelib
Version: 0.5.0
Summary: Une mini bibliothèque qui fait des additions comme un monstre
Author-email: Mohamed Echcharif EL JAZOULI <charif.eljazouli@email.com>
License: MIT
Project-URL: Homepage, https://github.com/Charifjaz/monstrelib
Requires-Python: >=3.7
Provides-Extra: dev
Requires-Dist: pytest; extra == "dev"
Requires-Dist: pytest-cov; extra == "dev"
Requires-Dist: pre-commit; extra == "dev"
